odoo/addons/stock_picking_product_assortment_availability_inline/README.rst
odoo/addons/stock_picking_product_assortment_availability_inline/__init__.py
odoo/addons/stock_picking_product_assortment_availability_inline/__manifest__.py
odoo/addons/stock_picking_product_assortment_availability_inline/i18n/it.po
odoo/addons/stock_picking_product_assortment_availability_inline/i18n/stock_picking_product_assortment_availability_inline.pot
odoo/addons/stock_picking_product_assortment_availability_inline/readme/CONTRIBUTORS.rst
odoo/addons/stock_picking_product_assortment_availability_inline/readme/DESCRIPTION.rst
odoo/addons/stock_picking_product_assortment_availability_inline/readme/USAGE.rst
odoo/addons/stock_picking_product_assortment_availability_inline/static/description/icon.png
odoo/addons/stock_picking_product_assortment_availability_inline/static/description/index.html
odoo_addon_stock_picking_product_assortment_availability_inline-15.0.2.0.0.dist-info/METADATA
odoo_addon_stock_picking_product_assortment_availability_inline-15.0.2.0.0.dist-info/WHEEL
odoo_addon_stock_picking_product_assortment_availability_inline-15.0.2.0.0.dist-info/top_level.txt
odoo_addon_stock_picking_product_assortment_availability_inline-15.0.2.0.0.dist-info/RECORD
