Metadata-Version: 2.1
Name: odoo-addon-stock_picking_product_assortment_availability_inline
Version: 15.0.2.0.0
Summary: Glue module to display stock available when an assortment is defined for a partner
Home-page: https://github.com/OCA/stock-logistics-workflow
Author: Tecnativa, Odoo Community Association (OCA)
Author-email: support@odoo-community.org
License: AGPL-3
Classifier: Programming Language :: Python
Classifier: Framework :: Odoo
Classifier: Framework :: Odoo :: 15.0
Classifier: License :: OSI Approved :: GNU Affero General Public License v3
Requires-Python: >=3.8
Requires-Dist: odoo-addon-stock-picking-product-assortment <15.1dev,>=15.0dev
Requires-Dist: odoo-addon-stock-picking-product-availability-inline <15.1dev,>=15.0dev
Requires-Dist: odoo <15.1dev,>=15.0a
